app.py
hexo_image_tool-0.0.1.dist-info/METADATA
hexo_image_tool-0.0.1.dist-info/WHEEL
hexo_image_tool-0.0.1.dist-info/entry_points.txt
hexo_image_tool-0.0.1.dist-info/top_level.txt
hexo_image_tool-0.0.1.dist-info/RECORD
