Metadata-Version: 2.1
Name: hexo-image-tool
Version: 0.0.1
Summary: Hexo image tool 
Home-page: https://github.com/donggangcj/ucs.git
Author: GangDong
Author-email: donggangcj@gmail.com
License: MIT Licence
Keywords: pip,hexo,COMMAND LINE
Platform: UNKNOWN
Requires-Dist: click
